msanic/__init__.py
msanic/base_blue.py
msanic/base_conf.py
msanic/base_server.py
msanic/base_ws.py
msanic/exception.py
msanic/handler_http.py
msanic/handler_ws.py
msanic/middleware.py
msanic/mult_creator.py
msanic/verify.py
msanic/libs/__init__.py
msanic/libs/base_timed.py
msanic/libs/component.py
msanic/libs/consts.py
msanic/libs/crypto.py
msanic/libs/decorator.py
msanic/libs/file_type.py
msanic/libs/manager.py
msanic/libs/mult_log.py
msanic/libs/random_maker.py
msanic/libs/rds_client.py
msanic/libs/rds_locker.py
msanic/libs/tool.py
msanic/libs/tool_dt.py
msanic/libs/tool_jwt.py
msanic/libs/tool_ws.py
msanic/orm/__init__.py
msanic/orm/db_index.py
msanic/orm/db_model.py
msanic/orm/mssql_generator.py
msanic/orm/mysql_generator.py
msanic/orm/pgsql_generator.py
msanic/orm/rc_model.py
test/__init__.py
test/test_unit.py
msanic-1.0.24.dist-info/LICENSE
msanic-1.0.24.dist-info/METADATA
msanic-1.0.24.dist-info/WHEEL
msanic-1.0.24.dist-info/entry_points.txt
msanic-1.0.24.dist-info/top_level.txt
msanic-1.0.24.dist-info/RECORD
